{"nodes": [{"id": "services_faq_context_service_py", "label": "faq_context_service.py", "file_type": "code", "source_file": "services\\faq_context_service.py", "source_location": "L1"}, {"id": "faq_context_service_build_faq_block", "label": "build_faq_block()", "file_type": "code", "source_file": "services\\faq_context_service.py", "source_location": "L37"}, {"id": "faq_context_service_rationale_1", "label": "FAQ as primary truth \u2014 runtime context builder.  Dumps every enabled FAQ entry", "file_type": "rationale", "source_file": "services\\faq_context_service.py", "source_location": "L1"}, {"id": "faq_context_service_rationale_38", "label": "Build the PRIMARY KNOWLEDGE block from the current hotel's enabled FAQ bank.", "file_type": "rationale", "source_file": "services\\faq_context_service.py", "source_location": "L38"}], "edges": [{"source": "services_faq_context_service_py", "target": "datetime", "relation": "imports_from", "confidence": "EXTRACTED", "source_file": "services\\faq_context_service.py", "source_location": "L14", "weight": 1.0}, {"source": "services_faq_context_service_py", "target": "logging", "relation": "imports", "confidence": "EXTRACTED", "source_file": "services\\faq_context_service.py", "source_location": "L15", "weight": 1.0}, {"source": "services_faq_context_service_py", "target": "faq_context_service_build_faq_block", "relation": "contains", "confidence": "EXTRACTED", "source_file": "services\\faq_context_service.py", "source_location": "L37", "weight": 1.0}, {"source": "faq_context_service_rationale_1", "target": "services_faq_context_service_py", "relation": "rationale_for", "confidence": "EXTRACTED", "source_file": "services\\faq_context_service.py", "source_location": "L1", "weight": 1.0}, {"source": "faq_context_service_rationale_38", "target": "faq_context_service_build_faq_block", "relation": "rationale_for", "confidence": "EXTRACTED", "source_file": "services\\faq_context_service.py", "source_location": "L38", "weight": 1.0}]}